{
"type": "FeatureCollection",
"name": "Bradford_Silver_Wood_summer_vga",
"crs": { "type": "name", "properties": { "name": "urn:ogc:def:crs:OGC:1.3:CRS84" } },
"features": [
{ "type": "Feature", "properties": { "visible_points": 1, "total_points": 1, "visibility_pct": 100.0 }, "geometry": { "type": "Point", "coordinates": [ -1.964484141338525, 53.816397311370828 ] } },
{ "type": "Feature", "properties": { "visible_points": 1, "total_points": 1, "visibility_pct": 100.0 }, "geometry": { "type": "Point", "coordinates": [ -1.964180373899866, 53.816397221391071 ] } }
]
}
