{
"type": "FeatureCollection",
"name": "Wakefield_Victoria_Park_and_Play_area_summer_vga",
"crs": { "type": "name", "properties": { "name": "urn:ogc:def:crs:OGC:1.3:CRS84" } },
"features": [
{ "type": "Feature", "properties": { "visible_points": 0, "total_points": 16, "visibility_pct": 0.0 }, "geometry": { "type": "Point", "coordinates": [ -1.34699429069345, 53.609556443730497 ] } },
{ "type": "Feature", "properties": { "visible_points": 10, "total_points": 16, "visibility_pct": 62.5 }, "geometry": { "type": "Point", "coordinates": [ -1.34699152196158, 53.609736199762004 ] } },
{ "type": "Feature", "properties": { "visible_points": 14, "total_points": 16, "visibility_pct": 87.5 }, "geometry": { "type": "Point", "coordinates": [ -1.346988753199323, 53.609915955788637 ] } },
{ "type": "Feature", "properties": { "visible_points": 14, "total_points": 16, "visibility_pct": 87.5 }, "geometry": { "type": "Point", "coordinates": [ -1.346985984406679, 53.610095711810402 ] } },
{ "type": "Feature", "properties": { "visible_points": 13, "total_points": 16, "visibility_pct": 81.25 }, "geometry": { "type": "Point", "coordinates": [ -1.346692032527622, 53.609554798318619 ] } },
{ "type": "Feature", "properties": { "visible_points": 12, "total_points": 16, "visibility_pct": 75.0 }, "geometry": { "type": "Point", "coordinates": [ -1.346689262493401, 53.609734554374143 ] } },
{ "type": "Feature", "properties": { "visible_points": 13, "total_points": 16, "visibility_pct": 81.25 }, "geometry": { "type": "Point", "coordinates": [ -1.346686492428778, 53.609914310424784 ] } },
{ "type": "Feature", "properties": { "visible_points": 14, "total_points": 16, "visibility_pct": 87.5 }, "geometry": { "type": "Point", "coordinates": [ -1.346683722333754, 53.610094066470566 ] } },
{ "type": "Feature", "properties": { "visible_points": 13, "total_points": 16, "visibility_pct": 81.25 }, "geometry": { "type": "Point", "coordinates": [ -1.346389774392149, 53.609553152142674 ] } },
{ "type": "Feature", "properties": { "visible_points": 12, "total_points": 16, "visibility_pct": 75.0 }, "geometry": { "type": "Point", "coordinates": [ -1.346387003055575, 53.609732908222199 ] } },
{ "type": "Feature", "properties": { "visible_points": 13, "total_points": 16, "visibility_pct": 81.25 }, "geometry": { "type": "Point", "coordinates": [ -1.346384231688587, 53.609912664296857 ] } },
{ "type": "Feature", "properties": { "visible_points": 14, "total_points": 16, "visibility_pct": 87.5 }, "geometry": { "type": "Point", "coordinates": [ -1.346381460291184, 53.610092420366634 ] } },
{ "type": "Feature", "properties": { "visible_points": 12, "total_points": 16, "visibility_pct": 75.0 }, "geometry": { "type": "Point", "coordinates": [ -1.346084743648118, 53.609731261306187 ] } },
{ "type": "Feature", "properties": { "visible_points": 13, "total_points": 16, "visibility_pct": 81.25 }, "geometry": { "type": "Point", "coordinates": [ -1.346081970978764, 53.609911017404841 ] } },
{ "type": "Feature", "properties": { "visible_points": 14, "total_points": 16, "visibility_pct": 87.5 }, "geometry": { "type": "Point", "coordinates": [ -1.346079198278982, 53.610090773498634 ] } },
{ "type": "Feature", "properties": { "visible_points": 0, "total_points": 16, "visibility_pct": 0.0 }, "geometry": { "type": "Point", "coordinates": [ -1.345779710299324, 53.609909369748756 ] } },
{ "type": "Feature", "properties": { "visible_points": 5, "total_points": 16, "visibility_pct": 31.25 }, "geometry": { "type": "Point", "coordinates": [ -1.345776936297163, 53.610089125866537 ] } }
]
}
