{
"type": "FeatureCollection",
"name": "Bradford_St_Pauls_Wood_OSM_benches_picnic",
"crs": { "type": "name", "properties": { "name": "urn:ogc:def:crs:OGC:1.3:CRS84" } },
"features": [
{ "type": "Feature", "properties": { "Park Feature": "Bench" }, "geometry": { "type": "Point", "coordinates": [ -1.7286988, 53.8540643 ] } },
{ "type": "Feature", "properties": { "Park Feature": "Bench" }, "geometry": { "type": "Point", "coordinates": [ -1.7303367, 53.8522862 ] } }
]
}
