{
"type": "FeatureCollection",
"name": "Wakefield_Ridings_Way_Park_park_street_lights",
"crs": { "type": "name", "properties": { "name": "urn:ogc:def:crs:OGC:1.3:CRS84" } },
"features": [
{ "type": "Feature", "properties": { "Park Feature": "Street Light" }, "geometry": { "type": "Point", "coordinates": [ -1.497236311669795, 53.723165060728988 ] } }
]
}
