{
"type": "FeatureCollection",
"name": "Kirklees_Cleckheaton_Library_Grounds_OSM_benches_picnic",
"crs": { "type": "name", "properties": { "name": "urn:ogc:def:crs:OGC:1.3:CRS84" } },
"features": [
{ "type": "Feature", "properties": { "Park Feature": "Bench" }, "geometry": { "type": "Point", "coordinates": [ -1.7123729, 53.7250151 ] } },
{ "type": "Feature", "properties": { "Park Feature": "Bench" }, "geometry": { "type": "Point", "coordinates": [ -1.7123689, 53.7250805 ] } },
{ "type": "Feature", "properties": { "Park Feature": "Bench" }, "geometry": { "type": "Point", "coordinates": [ -1.7121087, 53.7251317 ] } }
]
}
