{
"type": "FeatureCollection",
"name": "Leeds_Memorial_Garden_summer_vga",
"crs": { "type": "name", "properties": { "name": "urn:ogc:def:crs:OGC:1.3:CRS84" } },
"features": [
{ "type": "Feature", "properties": { "visible_points": 1, "total_points": 1, "visibility_pct": 100.0 }, "geometry": { "type": "Point", "coordinates": [ -1.706781478663712, 53.876132978971533 ] } },
{ "type": "Feature", "properties": { "visible_points": 1, "total_points": 1, "visibility_pct": 100.0 }, "geometry": { "type": "Point", "coordinates": [ -1.706477293021395, 53.876132238546468 ] } }
]
}
