{
"type": "FeatureCollection",
"name": "Leeds_Church_Wood_OSM_trees",
"crs": { "type": "name", "properties": { "name": "urn:ogc:def:crs:OGC:1.3:CRS84" } },
"features": [
{ "type": "Feature", "properties": { "Park Feature": "Tree" }, "geometry": { "type": "Point", "coordinates": [ -1.5803348, 53.8208566 ] } },
{ "type": "Feature", "properties": { "Park Feature": "Tree" }, "geometry": { "type": "Point", "coordinates": [ -1.5804581, 53.8208725 ] } },
{ "type": "Feature", "properties": { "Park Feature": "Tree" }, "geometry": { "type": "Point", "coordinates": [ -1.5805788, 53.8208693 ] } },
{ "type": "Feature", "properties": { "Park Feature": "Tree" }, "geometry": { "type": "Point", "coordinates": [ -1.580721, 53.8208725 ] } },
{ "type": "Feature", "properties": { "Park Feature": "Tree" }, "geometry": { "type": "Point", "coordinates": [ -1.5924403, 53.8264165 ] } }
]
}
