{
"type": "FeatureCollection",
"name": "Bradford_Holmes_Spring_summer_vga",
"crs": { "type": "name", "properties": { "name": "urn:ogc:def:crs:OGC:1.3:CRS84" } },
"features": [
{ "type": "Feature", "properties": { "visible_points": 0, "total_points": 4, "visibility_pct": 0.0 }, "geometry": { "type": "Point", "coordinates": [ -1.805156281394942, 53.932435330078128 ] } },
{ "type": "Feature", "properties": { "visible_points": 0, "total_points": 4, "visibility_pct": 0.0 }, "geometry": { "type": "Point", "coordinates": [ -1.805155446890648, 53.932615083449946 ] } },
{ "type": "Feature", "properties": { "visible_points": 0, "total_points": 4, "visibility_pct": 0.0 }, "geometry": { "type": "Point", "coordinates": [ -1.804851675238677, 53.932434838516166 ] } },
{ "type": "Feature", "properties": { "visible_points": 0, "total_points": 4, "visibility_pct": 0.0 }, "geometry": { "type": "Point", "coordinates": [ -1.804850839419511, 53.932614591875101 ] } },
{ "type": "Feature", "properties": { "visible_points": 0, "total_points": 4, "visibility_pct": 0.0 }, "geometry": { "type": "Point", "coordinates": [ -1.804547069091598, 53.932434346181687 ] } }
]
}
