{
"type": "FeatureCollection",
"name": "Leeds_Crossley_Park_Wood_summer_vga",
"crs": { "type": "name", "properties": { "name": "urn:ogc:def:crs:OGC:1.3:CRS84" } },
"features": [
{ "type": "Feature", "properties": { "visible_points": 0, "total_points": 4, "visibility_pct": 0.0 }, "geometry": { "type": "Point", "coordinates": [ -1.394346766841243, 53.929573935388575 ] } },
{ "type": "Feature", "properties": { "visible_points": 0, "total_points": 4, "visibility_pct": 0.0 }, "geometry": { "type": "Point", "coordinates": [ -1.394042192119332, 53.929572402111901 ] } },
{ "type": "Feature", "properties": { "visible_points": 0, "total_points": 4, "visibility_pct": 0.0 }, "geometry": { "type": "Point", "coordinates": [ -1.393737617425672, 53.929570868062882 ] } },
{ "type": "Feature", "properties": { "visible_points": 0, "total_points": 4, "visibility_pct": 0.0 }, "geometry": { "type": "Point", "coordinates": [ -1.393430439830731, 53.929749076172747 ] } },
{ "type": "Feature", "properties": { "visible_points": 0, "total_points": 4, "visibility_pct": 0.0 }, "geometry": { "type": "Point", "coordinates": [ -1.393125863891174, 53.929747540568606 ] } }
]
}
