{
"type": "FeatureCollection",
"name": "Leeds_Primrose_Valley_Park_OSM_benches_picnic",
"crs": { "type": "name", "properties": { "name": "urn:ogc:def:crs:OGC:1.3:CRS84" } },
"features": [
{ "type": "Feature", "properties": { "Park Feature": "Bench" }, "geometry": { "type": "Point", "coordinates": [ -1.4708372, 53.7933052 ] } }
]
}
