{
"type": "FeatureCollection",
"name": "Wakefield_Huntwick_Whin_OSM_park_features_general",
"crs": { "type": "name", "properties": { "name": "urn:ogc:def:crs:OGC:1.3:CRS84" } },
"features": [
{ "type": "Feature", "properties": { "Park Feature": "Board" }, "geometry": { "type": "Point", "coordinates": [ -1.3861355, 53.6621329 ] } },
{ "type": "Feature", "properties": { "Park Feature": "Board" }, "geometry": { "type": "Point", "coordinates": [ -1.3859823, 53.6621232 ] } }
]
}
