{
"type": "FeatureCollection",
"name": "Bradford_Kashmir_Park_external_entrances",
"crs": { "type": "name", "properties": { "name": "urn:ogc:def:crs:OGC:1.3:CRS84" } },
"features": [
{ "type": "Feature", "properties": { "id": "409D2663-C155-42E8-B5BB-06A17644E1C0", "access_type": "Pedestrian", "Park Name": "Lister Park", "Park Segment Name": "Lister Park", "source": "OS", "highway_type": null }, "geometry": { "type": "Point", "coordinates": [ -1.77636180019418, 53.81278683536555 ] } },
{ "type": "Feature", "properties": { "id": null, "access_type": "foot", "Park Name": "Lister Park", "Park Segment Name": "Lister Park", "source": "calculated", "highway_type": "path" }, "geometry": { "type": "Point", "coordinates": [ -1.776349756865804, 53.812781093617076 ] } },
{ "type": "Feature", "properties": { "id": "AA8C028A-B4DA-4E8C-B036-5EF85FDCDBE9", "access_type": "Motor Vehicle And Pedestrian", "Park Name": "Kashmir Park", "Park Segment Name": "Kashmir Park", "source": "OS", "highway_type": null }, "geometry": { "type": "Point", "coordinates": [ -1.787155782859398, 53.809625459199054 ] } },
{ "type": "Feature", "properties": { "id": "04B97D4C-2716-47AD-84EF-B05C9FCBB232", "access_type": "Pedestrian", "Park Name": "Kashmir Park", "Park Segment Name": "Kashmir Park", "source": "OS", "highway_type": null }, "geometry": { "type": "Point", "coordinates": [ -1.788315087878346, 53.808080130790408 ] } },
{ "type": "Feature", "properties": { "id": "00575BD8-2AE3-4919-825F-27530057E7B4", "access_type": "Motor Vehicle And Pedestrian", "Park Name": "Kashmir Park", "Park Segment Name": "Kashmir Park", "source": "OS", "highway_type": null }, "geometry": { "type": "Point", "coordinates": [ -1.787554843251853, 53.808063873122293 ] } },
{ "type": "Feature", "properties": { "id": "D0872093-BEE0-4697-9D66-786CE250D8B6", "access_type": "Motor Vehicle And Pedestrian", "Park Name": "Kashmir Park", "Park Segment Name": "Kashmir Park", "source": "OS", "highway_type": null }, "geometry": { "type": "Point", "coordinates": [ -1.787861099013053, 53.809517768524245 ] } },
{ "type": "Feature", "properties": { "id": "B9121D7B-9162-49A3-BF50-87813A9C1D63", "access_type": "Pedestrian", "Park Name": "Kashmir Park", "Park Segment Name": "Kashmir Park", "source": "OS", "highway_type": null }, "geometry": { "type": "Point", "coordinates": [ -1.787931630939562, 53.809262903393048 ] } },
{ "type": "Feature", "properties": { "id": "8381963D-9E0F-425A-9A34-233AA0AA6C6B", "access_type": "Pedestrian", "Park Name": "Kashmir Park", "Park Segment Name": "Kashmir Park", "source": "OS", "highway_type": null }, "geometry": { "type": "Point", "coordinates": [ -1.787660708548285, 53.808089315832738 ] } },
{ "type": "Feature", "properties": { "id": "CC838B19-5628-470D-B08F-CF229D2981AB", "access_type": "Motor Vehicle And Pedestrian", "Park Name": "Kashmir Park", "Park Segment Name": "Kashmir Park", "source": "OS", "highway_type": null }, "geometry": { "type": "Point", "coordinates": [ -1.785827318316592, 53.808253427466475 ] } },
{ "type": "Feature", "properties": { "id": null, "access_type": "foot", "Park Name": "Kashmir Park", "Park Segment Name": "Kashmir Park", "source": "calculated", "highway_type": "footway" }, "geometry": { "type": "Point", "coordinates": [ -1.78796620000001, 53.809278900000024 ] } },
{ "type": "Feature", "properties": { "id": null, "access_type": "foot", "Park Name": "Kashmir Park", "Park Segment Name": "Kashmir Park", "source": "calculated", "highway_type": "footway" }, "geometry": { "type": "Point", "coordinates": [ -1.7883376, 53.8080747 ] } },
{ "type": "Feature", "properties": { "id": null, "access_type": "foot", "Park Name": "Kashmir Park", "Park Segment Name": "Kashmir Park", "source": "calculated", "highway_type": "footway" }, "geometry": { "type": "Point", "coordinates": [ -1.787647, 53.8080718 ] } },
{ "type": "Feature", "properties": { "id": "62A63359-7508-452F-95BA-7F2438DD1672", "access_type": "Motor Vehicle And Pedestrian", "Park Name": "Heaton Hill", "Park Segment Name": "Heaton Hill", "source": "OS", "highway_type": null }, "geometry": { "type": "Point", "coordinates": [ -1.788839287708712, 53.81609617696607 ] } },
{ "type": "Feature", "properties": { "id": null, "access_type": "vehicle", "Park Name": "Heaton Hill", "Park Segment Name": "Heaton Hill", "source": "calculated", "highway_type": "service" }, "geometry": { "type": "Point", "coordinates": [ -1.78881480253811, 53.816093435663092 ] } },
{ "type": "Feature", "properties": { "id": "4A95840B-D119-4C2B-B817-F920001FD02F", "access_type": "Pedestrian", "Park Name": "West Park, Girlington", "Park Segment Name": "West Park, Girlington", "source": "OS", "highway_type": null }, "geometry": { "type": "Point", "coordinates": [ -1.791117584248078, 53.801585470331446 ] } }
]
}
