{
"type": "FeatureCollection",
"name": "Leeds_Beulah_Wood_OSM_trees",
"crs": { "type": "name", "properties": { "name": "urn:ogc:def:crs:OGC:1.3:CRS84" } },
"features": [
{ "type": "Feature", "properties": { "Park Feature": "Tree" }, "geometry": { "type": "Point", "coordinates": [ -1.6277179, 53.7864322 ] } },
{ "type": "Feature", "properties": { "Park Feature": "Tree" }, "geometry": { "type": "Point", "coordinates": [ -1.627431, 53.7864975 ] } },
{ "type": "Feature", "properties": { "Park Feature": "Tree" }, "geometry": { "type": "Point", "coordinates": [ -1.6272696, 53.7866635 ] } },
{ "type": "Feature", "properties": { "Park Feature": "Tree" }, "geometry": { "type": "Point", "coordinates": [ -1.6274698, 53.7867571 ] } },
{ "type": "Feature", "properties": { "Park Feature": "Tree" }, "geometry": { "type": "Point", "coordinates": [ -1.6271202, 53.7868471 ] } }
]
}
