{
"type": "FeatureCollection",
"name": "Calderdale_Rastrick_Library_Gardens_summer_vga",
"crs": { "type": "name", "properties": { "name": "urn:ogc:def:crs:OGC:1.3:CRS84" } },
"features": [
{ "type": "Feature", "properties": { "visible_points": 0, "total_points": 4, "visibility_pct": 0.0 }, "geometry": { "type": "Point", "coordinates": [ -1.795238831174564, 53.688849497600458 ] } },
{ "type": "Feature", "properties": { "visible_points": 0, "total_points": 4, "visibility_pct": 0.0 }, "geometry": { "type": "Point", "coordinates": [ -1.795237966019216, 53.689029260790832 ] } },
{ "type": "Feature", "properties": { "visible_points": 0, "total_points": 4, "visibility_pct": 0.0 }, "geometry": { "type": "Point", "coordinates": [ -1.794935118258212, 53.689028744555401 ] } },
{ "type": "Feature", "properties": { "visible_points": 0, "total_points": 4, "visibility_pct": 0.0 }, "geometry": { "type": "Point", "coordinates": [ -1.794633138245153, 53.688848464361413 ] } },
{ "type": "Feature", "properties": { "visible_points": 0, "total_points": 4, "visibility_pct": 0.0 }, "geometry": { "type": "Point", "coordinates": [ -1.794330291794676, 53.688847946593221 ] } }
]
}
