{
"type": "FeatureCollection",
"name": "Leeds_Wellcroft_Park_summer_vga",
"crs": { "type": "name", "properties": { "name": "urn:ogc:def:crs:OGC:1.3:CRS84" } },
"features": [
{ "type": "Feature", "properties": { "visible_points": 0, "total_points": 21, "visibility_pct": 0.0 }, "geometry": { "type": "Point", "coordinates": [ -1.688344592330471, 53.904331453354786 ] } },
{ "type": "Feature", "properties": { "visible_points": 18, "total_points": 22, "visibility_pct": 81.818181818181827 }, "geometry": { "type": "Point", "coordinates": [ -1.688343255079912, 53.904511207256647 ] } },
{ "type": "Feature", "properties": { "visible_points": 17, "total_points": 22, "visibility_pct": 77.272727272727266 }, "geometry": { "type": "Point", "coordinates": [ -1.688341917814685, 53.904690961153094 ] } },
{ "type": "Feature", "properties": { "visible_points": 17, "total_points": 21, "visibility_pct": 80.952380952380949 }, "geometry": { "type": "Point", "coordinates": [ -1.688340580534792, 53.904870715044133 ] } },
{ "type": "Feature", "properties": { "visible_points": 18, "total_points": 20, "visibility_pct": 90.0 }, "geometry": { "type": "Point", "coordinates": [ -1.688339243240231, 53.90505046892978 ] } },
{ "type": "Feature", "properties": { "visible_points": 4, "total_points": 21, "visibility_pct": 19.047619047619047 }, "geometry": { "type": "Point", "coordinates": [ -1.688040193199517, 53.904330663412765 ] } },
{ "type": "Feature", "properties": { "visible_points": 17, "total_points": 22, "visibility_pct": 77.272727272727266 }, "geometry": { "type": "Point", "coordinates": [ -1.688038854636895, 53.904510417310938 ] } },
{ "type": "Feature", "properties": { "visible_points": 16, "total_points": 22, "visibility_pct": 72.727272727272734 }, "geometry": { "type": "Point", "coordinates": [ -1.688037516059592, 53.904690171203697 ] } },
{ "type": "Feature", "properties": { "visible_points": 16, "total_points": 22, "visibility_pct": 72.727272727272734 }, "geometry": { "type": "Point", "coordinates": [ -1.688036177467608, 53.904869925091077 ] } },
{ "type": "Feature", "properties": { "visible_points": 17, "total_points": 21, "visibility_pct": 80.952380952380949 }, "geometry": { "type": "Point", "coordinates": [ -1.688034838860943, 53.905049678973043 ] } },
{ "type": "Feature", "properties": { "visible_points": 8, "total_points": 21, "visibility_pct": 38.095238095238095 }, "geometry": { "type": "Point", "coordinates": [ -1.687735794083212, 53.904329872698945 ] } },
{ "type": "Feature", "properties": { "visible_points": 17, "total_points": 22, "visibility_pct": 77.272727272727266 }, "geometry": { "type": "Point", "coordinates": [ -1.687734454208528, 53.904509626593452 ] } },
{ "type": "Feature", "properties": { "visible_points": 17, "total_points": 22, "visibility_pct": 77.272727272727266 }, "geometry": { "type": "Point", "coordinates": [ -1.687733114319149, 53.904689380482537 ] } },
{ "type": "Feature", "properties": { "visible_points": 18, "total_points": 22, "visibility_pct": 81.818181818181827 }, "geometry": { "type": "Point", "coordinates": [ -1.687731774415074, 53.90486913436623 ] } },
{ "type": "Feature", "properties": { "visible_points": 17, "total_points": 21, "visibility_pct": 80.952380952380949 }, "geometry": { "type": "Point", "coordinates": [ -1.687730434496304, 53.905048888244494 ] } },
{ "type": "Feature", "properties": { "visible_points": 18, "total_points": 22, "visibility_pct": 81.818181818181827 }, "geometry": { "type": "Point", "coordinates": [ -1.68743139498157, 53.904329081213362 ] } },
{ "type": "Feature", "properties": { "visible_points": 17, "total_points": 22, "visibility_pct": 77.272727272727266 }, "geometry": { "type": "Point", "coordinates": [ -1.687430053794825, 53.904508835104188 ] } },
{ "type": "Feature", "properties": { "visible_points": 13, "total_points": 22, "visibility_pct": 59.090909090909093 }, "geometry": { "type": "Point", "coordinates": [ -1.68742871259337, 53.904688588989586 ] } },
{ "type": "Feature", "properties": { "visible_points": 16, "total_points": 22, "visibility_pct": 72.727272727272734 }, "geometry": { "type": "Point", "coordinates": [ -1.687427371377205, 53.904868342869584 ] } },
{ "type": "Feature", "properties": { "visible_points": 18, "total_points": 21, "visibility_pct": 85.714285714285708 }, "geometry": { "type": "Point", "coordinates": [ -1.68742603014633, 53.905048096744196 ] } },
{ "type": "Feature", "properties": { "visible_points": 17, "total_points": 17, "visibility_pct": 100.0 }, "geometry": { "type": "Point", "coordinates": [ -1.687424688900746, 53.905227850613386 ] } },
{ "type": "Feature", "properties": { "visible_points": 0, "total_points": 16, "visibility_pct": 0.0 }, "geometry": { "type": "Point", "coordinates": [ -1.68712833837869, 53.904148535063491 ] } },
{ "type": "Feature", "properties": { "visible_points": 0, "total_points": 20, "visibility_pct": 0.0 }, "geometry": { "type": "Point", "coordinates": [ -1.687126995894607, 53.904328288956023 ] } }
]
}
