{
"type": "FeatureCollection",
"name": "Bradford_Mayfield_Cc_OSM_benches_picnic",
"crs": { "type": "name", "properties": { "name": "urn:ogc:def:crs:OGC:1.3:CRS84" } },
"features": [
{ "type": "Feature", "properties": { "Park Feature": "Bench" }, "geometry": { "type": "Point", "coordinates": [ -1.8242431, 53.7852178 ] } }
]
}
