{
"type": "FeatureCollection",
"name": "Calderdale_Salem_Cricket_Ground_summer_vga",
"crs": { "type": "name", "properties": { "name": "urn:ogc:def:crs:OGC:1.3:CRS84" } },
"features": [
{ "type": "Feature", "properties": { "visible_points": 7, "total_points": 9, "visibility_pct": 77.777777777777786 }, "geometry": { "type": "Point", "coordinates": [ -2.014184851229244, 53.747572803668746 ] } },
{ "type": "Feature", "properties": { "visible_points": 10, "total_points": 12, "visibility_pct": 83.333333333333343 }, "geometry": { "type": "Point", "coordinates": [ -2.014184915904445, 53.747752563754794 ] } },
{ "type": "Feature", "properties": { "visible_points": 13, "total_points": 14, "visibility_pct": 92.857142857142861 }, "geometry": { "type": "Point", "coordinates": [ -2.014184980580241, 53.747932323835443 ] } },
{ "type": "Feature", "properties": { "visible_points": 14, "total_points": 15, "visibility_pct": 93.333333333333329 }, "geometry": { "type": "Point", "coordinates": [ -2.014185045256631, 53.748112083910677 ] } },
{ "type": "Feature", "properties": { "visible_points": 14, "total_points": 15, "visibility_pct": 93.333333333333329 }, "geometry": { "type": "Point", "coordinates": [ -2.014185109933616, 53.748291843980525 ] } },
{ "type": "Feature", "properties": { "visible_points": 14, "total_points": 15, "visibility_pct": 93.333333333333329 }, "geometry": { "type": "Point", "coordinates": [ -2.014185174611197, 53.748471604044958 ] } },
{ "type": "Feature", "properties": { "visible_points": 12, "total_points": 13, "visibility_pct": 92.307692307692307 }, "geometry": { "type": "Point", "coordinates": [ -2.014185239289371, 53.748651364103985 ] } },
{ "type": "Feature", "properties": { "visible_points": 4, "total_points": 12, "visibility_pct": 33.333333333333329 }, "geometry": { "type": "Point", "coordinates": [ -2.013881644224078, 53.747752599831415 ] } },
{ "type": "Feature", "properties": { "visible_points": 0, "total_points": 14, "visibility_pct": 0.0 }, "geometry": { "type": "Point", "coordinates": [ -2.013881707584869, 53.747932359905185 ] } },
{ "type": "Feature", "properties": { "visible_points": 13, "total_points": 15, "visibility_pct": 86.666666666666671 }, "geometry": { "type": "Point", "coordinates": [ -2.013881770946239, 53.748112119973548 ] } },
{ "type": "Feature", "properties": { "visible_points": 13, "total_points": 15, "visibility_pct": 86.666666666666671 }, "geometry": { "type": "Point", "coordinates": [ -2.013881834308191, 53.748291880036511 ] } },
{ "type": "Feature", "properties": { "visible_points": 12, "total_points": 14, "visibility_pct": 85.714285714285708 }, "geometry": { "type": "Point", "coordinates": [ -2.013881897670723, 53.748471640094067 ] } },
{ "type": "Feature", "properties": { "visible_points": 11, "total_points": 13, "visibility_pct": 84.615384615384613 }, "geometry": { "type": "Point", "coordinates": [ -2.013881961033836, 53.74865140014623 ] } },
{ "type": "Feature", "properties": { "visible_points": 12, "total_points": 14, "visibility_pct": 85.714285714285708 }, "geometry": { "type": "Point", "coordinates": [ -2.013578620729624, 53.748471675375782 ] } },
{ "type": "Feature", "properties": { "visible_points": 11, "total_points": 12, "visibility_pct": 91.666666666666657 }, "geometry": { "type": "Point", "coordinates": [ -2.013578682777675, 53.748651435421053 ] } },
{ "type": "Feature", "properties": { "visible_points": 10, "total_points": 10, "visibility_pct": 100.0 }, "geometry": { "type": "Point", "coordinates": [ -2.013578744826292, 53.748831195460923 ] } }
]
}
