{
"type": "FeatureCollection",
"name": "Bradford_St_Margarets_Park_summer_vga",
"crs": { "type": "name", "properties": { "name": "urn:ogc:def:crs:OGC:1.3:CRS84" } },
"features": [
{ "type": "Feature", "properties": { "visible_points": 0, "total_points": 16, "visibility_pct": 0.0 }, "geometry": { "type": "Point", "coordinates": [ -1.827208932871173, 53.921537718150894 ] } },
{ "type": "Feature", "properties": { "visible_points": 0, "total_points": 16, "visibility_pct": 0.0 }, "geometry": { "type": "Point", "coordinates": [ -1.827208194251092, 53.921717472420561 ] } },
{ "type": "Feature", "properties": { "visible_points": 0, "total_points": 16, "visibility_pct": 0.0 }, "geometry": { "type": "Point", "coordinates": [ -1.827207455622837, 53.921897226684784 ] } },
{ "type": "Feature", "properties": { "visible_points": 0, "total_points": 16, "visibility_pct": 0.0 }, "geometry": { "type": "Point", "coordinates": [ -1.827206716986409, 53.922076980943601 ] } },
{ "type": "Feature", "properties": { "visible_points": 0, "total_points": 16, "visibility_pct": 0.0 }, "geometry": { "type": "Point", "coordinates": [ -1.827205978341808, 53.922256735197024 ] } },
{ "type": "Feature", "properties": { "visible_points": 0, "total_points": 16, "visibility_pct": 0.0 }, "geometry": { "type": "Point", "coordinates": [ -1.826904403048526, 53.921537281249002 ] } },
{ "type": "Feature", "properties": { "visible_points": 0, "total_points": 16, "visibility_pct": 0.0 }, "geometry": { "type": "Point", "coordinates": [ -1.826903663114585, 53.921717035513154 ] } },
{ "type": "Feature", "properties": { "visible_points": 0, "total_points": 16, "visibility_pct": 0.0 }, "geometry": { "type": "Point", "coordinates": [ -1.826902923172456, 53.921896789771885 ] } },
{ "type": "Feature", "properties": { "visible_points": 0, "total_points": 16, "visibility_pct": 0.0 }, "geometry": { "type": "Point", "coordinates": [ -1.826902183222139, 53.922076544025224 ] } },
{ "type": "Feature", "properties": { "visible_points": 0, "total_points": 16, "visibility_pct": 0.0 }, "geometry": { "type": "Point", "coordinates": [ -1.826901443263635, 53.922256298273126 ] } },
{ "type": "Feature", "properties": { "visible_points": 0, "total_points": 16, "visibility_pct": 0.0 }, "geometry": { "type": "Point", "coordinates": [ -1.826599131986221, 53.921716597833516 ] } },
{ "type": "Feature", "properties": { "visible_points": 0, "total_points": 16, "visibility_pct": 0.0 }, "geometry": { "type": "Point", "coordinates": [ -1.826598390730218, 53.921896352086733 ] } },
{ "type": "Feature", "properties": { "visible_points": 0, "total_points": 16, "visibility_pct": 0.0 }, "geometry": { "type": "Point", "coordinates": [ -1.826597649466013, 53.922076106334558 ] } },
{ "type": "Feature", "properties": { "visible_points": 0, "total_points": 16, "visibility_pct": 0.0 }, "geometry": { "type": "Point", "coordinates": [ -1.826596908193607, 53.922255860576968 ] } },
{ "type": "Feature", "properties": { "visible_points": 0, "total_points": 16, "visibility_pct": 0.0 }, "geometry": { "type": "Point", "coordinates": [ -1.826293858296139, 53.921895913629328 ] } },
{ "type": "Feature", "properties": { "visible_points": 0, "total_points": 16, "visibility_pct": 0.0 }, "geometry": { "type": "Point", "coordinates": [ -1.826293115718045, 53.922075667871638 ] } },
{ "type": "Feature", "properties": { "visible_points": 0, "total_points": 16, "visibility_pct": 0.0 }, "geometry": { "type": "Point", "coordinates": [ -1.826292373131736, 53.922255422108542 ] } }
]
}
