{
"type": "FeatureCollection",
"name": "Bradford_Grange_Park_OSM_trees",
"crs": { "type": "name", "properties": { "name": "urn:ogc:def:crs:OGC:1.3:CRS84" } },
"features": [
{ "type": "Feature", "properties": { "Park Feature": "Tree" }, "geometry": { "type": "Point", "coordinates": [ -1.7419252, 53.9122574 ] } },
{ "type": "Feature", "properties": { "Park Feature": "Tree" }, "geometry": { "type": "Point", "coordinates": [ -1.7494307, 53.9133505 ] } },
{ "type": "Feature", "properties": { "Park Feature": "Tree" }, "geometry": { "type": "Point", "coordinates": [ -1.7461061, 53.9126964 ] } },
{ "type": "Feature", "properties": { "Park Feature": "Tree" }, "geometry": { "type": "Point", "coordinates": [ -1.7459465, 53.9128473 ] } },
{ "type": "Feature", "properties": { "Park Feature": "Tree" }, "geometry": { "type": "Point", "coordinates": [ -1.7456769, 53.9128987 ] } },
{ "type": "Feature", "properties": { "Park Feature": "Tree" }, "geometry": { "type": "Point", "coordinates": [ -1.7491893, 53.913559 ] } },
{ "type": "Feature", "properties": { "Park Feature": "Tree" }, "geometry": { "type": "Point", "coordinates": [ -1.7490967, 53.9135077 ] } },
{ "type": "Feature", "properties": { "Park Feature": "Tree" }, "geometry": { "type": "Point", "coordinates": [ -1.749841, 53.9136317 ] } },
{ "type": "Feature", "properties": { "Park Feature": "Tree" }, "geometry": { "type": "Point", "coordinates": [ -1.7495637, 53.9135069 ] } },
{ "type": "Feature", "properties": { "Park Feature": "Tree" }, "geometry": { "type": "Point", "coordinates": [ -1.7488138, 53.9128987 ] } },
{ "type": "Feature", "properties": { "Park Feature": "Tree" }, "geometry": { "type": "Point", "coordinates": [ -1.7486461, 53.9131735 ] } },
{ "type": "Feature", "properties": { "Park Feature": "Tree" }, "geometry": { "type": "Point", "coordinates": [ -1.7492644, 53.9132438 ] } },
{ "type": "Feature", "properties": { "Park Feature": "Tree" }, "geometry": { "type": "Point", "coordinates": [ -1.7489358, 53.9132612 ] } },
{ "type": "Feature", "properties": { "Park Feature": "Tree" }, "geometry": { "type": "Point", "coordinates": [ -1.7491638, 53.9133371 ] } },
{ "type": "Feature", "properties": { "Park Feature": "Tree" }, "geometry": { "type": "Point", "coordinates": [ -1.7490887, 53.913439 ] } },
{ "type": "Feature", "properties": { "Park Feature": "Tree" }, "geometry": { "type": "Point", "coordinates": [ -1.7492805, 53.913337 ] } },
{ "type": "Feature", "properties": { "Park Feature": "Tree" }, "geometry": { "type": "Point", "coordinates": [ -1.7493046, 53.9135187 ] } },
{ "type": "Feature", "properties": { "Park Feature": "Tree" }, "geometry": { "type": "Point", "coordinates": [ -1.7462683, 53.9130258 ] } },
{ "type": "Feature", "properties": { "Park Feature": "Tree" }, "geometry": { "type": "Point", "coordinates": [ -1.7464212, 53.9130163 ] } },
{ "type": "Feature", "properties": { "Park Feature": "Tree" }, "geometry": { "type": "Point", "coordinates": [ -1.7492328, 53.9129505 ] } },
{ "type": "Feature", "properties": { "Park Feature": "Tree" }, "geometry": { "type": "Point", "coordinates": [ -1.7490878, 53.9129432 ] } },
{ "type": "Feature", "properties": { "Park Feature": "Tree" }, "geometry": { "type": "Point", "coordinates": [ -1.7491125, 53.9128469 ] } },
{ "type": "Feature", "properties": { "Park Feature": "Tree" }, "geometry": { "type": "Point", "coordinates": [ -1.7493038, 53.9128451 ] } },
{ "type": "Feature", "properties": { "Park Feature": "Tree" }, "geometry": { "type": "Point", "coordinates": [ -1.7494025, 53.913114 ] } },
{ "type": "Feature", "properties": { "Park Feature": "Tree" }, "geometry": { "type": "Point", "coordinates": [ -1.7503609, 53.9150894 ] } },
{ "type": "Feature", "properties": { "Park Feature": "Tree" }, "geometry": { "type": "Point", "coordinates": [ -1.7448357, 53.9144929 ] } },
{ "type": "Feature", "properties": { "Park Feature": "Tree" }, "geometry": { "type": "Point", "coordinates": [ -1.7460779, 53.9145179 ] } },
{ "type": "Feature", "properties": { "Park Feature": "Tree" }, "geometry": { "type": "Point", "coordinates": [ -1.7473647, 53.9146202 ] } },
{ "type": "Feature", "properties": { "Park Feature": "Tree" }, "geometry": { "type": "Point", "coordinates": [ -1.7442681, 53.9135445 ] } },
{ "type": "Feature", "properties": { "Park Feature": "Tree" }, "geometry": { "type": "Point", "coordinates": [ -1.7441393, 53.9136461 ] } },
{ "type": "Feature", "properties": { "Park Feature": "Tree" }, "geometry": { "type": "Point", "coordinates": [ -1.7440032, 53.9137477 ] } },
{ "type": "Feature", "properties": { "Park Feature": "Tree" }, "geometry": { "type": "Point", "coordinates": [ -1.7437748, 53.9139481 ] } }
]
}
