{
"type": "FeatureCollection",
"name": "Leeds_Sovereign_Square_OSM_park_features_general",
"crs": { "type": "name", "properties": { "name": "urn:ogc:def:crs:OGC:1.3:CRS84" } },
"features": [
{ "type": "Feature", "properties": { "Park Feature": "Recycling" }, "geometry": { "type": "Point", "coordinates": [ -1.5340939, 53.7972092 ] } },
{ "type": "Feature", "properties": { "Park Feature": "Waste Basket" }, "geometry": { "type": "Point", "coordinates": [ -1.5526131, 53.7989588 ] } },
{ "type": "Feature", "properties": { "Park Feature": "Waste Basket" }, "geometry": { "type": "Point", "coordinates": [ -1.552605, 53.798976 ] } },
{ "type": "Feature", "properties": { "Park Feature": "Waste Basket" }, "geometry": { "type": "Point", "coordinates": [ -1.5523503, 53.7991176 ] } },
{ "type": "Feature", "properties": { "Park Feature": "Waste Basket" }, "geometry": { "type": "Point", "coordinates": [ -1.5518423, 53.799068 ] } },
{ "type": "Feature", "properties": { "Park Feature": "Waste Basket" }, "geometry": { "type": "Point", "coordinates": [ -1.5518742, 53.7990708 ] } },
{ "type": "Feature", "properties": { "Park Feature": "Waste Basket" }, "geometry": { "type": "Point", "coordinates": [ -1.5518451, 53.7990456 ] } },
{ "type": "Feature", "properties": { "Park Feature": "Waste Basket" }, "geometry": { "type": "Point", "coordinates": [ -1.5518782, 53.79905 ] } },
{ "type": "Feature", "properties": { "Park Feature": "Waste Basket" }, "geometry": { "type": "Point", "coordinates": [ -1.5518566, 53.7989852 ] } },
{ "type": "Feature", "properties": { "Park Feature": "Waste Basket" }, "geometry": { "type": "Point", "coordinates": [ -1.5519026, 53.79899 ] } },
{ "type": "Feature", "properties": { "Park Feature": "Waste Basket" }, "geometry": { "type": "Point", "coordinates": [ -1.5520124, 53.7987504 ] } },
{ "type": "Feature", "properties": { "Park Feature": "Waste Basket" }, "geometry": { "type": "Point", "coordinates": [ -1.5520361, 53.7986895 ] } },
{ "type": "Feature", "properties": { "Park Feature": "Waste Basket" }, "geometry": { "type": "Point", "coordinates": [ -1.5519975, 53.7986815 ] } },
{ "type": "Feature", "properties": { "Park Feature": "Waste Basket" }, "geometry": { "type": "Point", "coordinates": [ -1.5520069, 53.7986619 ] } },
{ "type": "Feature", "properties": { "Park Feature": "Waste Basket" }, "geometry": { "type": "Point", "coordinates": [ -1.5520462, 53.7986683 ] } },
{ "type": "Feature", "properties": { "Park Feature": "Waste Basket" }, "geometry": { "type": "Point", "coordinates": [ -1.5512443, 53.7987508 ] } },
{ "type": "Feature", "properties": { "Park Feature": "Waste Basket" }, "geometry": { "type": "Point", "coordinates": [ -1.5512362, 53.7987692 ] } },
{ "type": "Feature", "properties": { "Park Feature": "Waste Basket" }, "geometry": { "type": "Point", "coordinates": [ -1.5514922, 53.7985867 ] } },
{ "type": "Feature", "properties": { "Park Feature": "Waste Basket" }, "geometry": { "type": "Point", "coordinates": [ -1.5517507, 53.798829 ] } },
{ "type": "Feature", "properties": { "Park Feature": "Waste Basket" }, "geometry": { "type": "Point", "coordinates": [ -1.5521313, 53.7988923 ] } }
]
}
