{
"type": "FeatureCollection",
"name": "Kirklees_Square_Spring_OSM_park_features_general",
"crs": { "type": "name", "properties": { "name": "urn:ogc:def:crs:OGC:1.3:CRS84" } },
"features": [
{ "type": "Feature", "properties": { "Park Feature": "Board" }, "geometry": { "type": "Point", "coordinates": [ -1.6087938, 53.5779266 ] } },
{ "type": "Feature", "properties": { "Park Feature": "Board" }, "geometry": { "type": "Point", "coordinates": [ -1.6107755, 53.588527 ] } }
]
}
