{
"type": "FeatureCollection",
"name": "Leeds_Seacroft_Gardens_OSM_trees",
"crs": { "type": "name", "properties": { "name": "urn:ogc:def:crs:OGC:1.3:CRS84" } },
"features": [
{ "type": "Feature", "properties": { "Park Feature": "Tree" }, "geometry": { "type": "Point", "coordinates": [ -1.4850475, 53.8155095 ] } }
]
}
