{
"type": "FeatureCollection",
"name": "Leeds_Wrinkle_Hill_Wood_summer_vga",
"crs": { "type": "name", "properties": { "name": "urn:ogc:def:crs:OGC:1.3:CRS84" } },
"features": [
{ "type": "Feature", "properties": { "visible_points": 0, "total_points": 18, "visibility_pct": 0.0 }, "geometry": { "type": "Point", "coordinates": [ -1.619793394742886, 53.86915783567828 ] } },
{ "type": "Feature", "properties": { "visible_points": 7, "total_points": 18, "visibility_pct": 38.888888888888893 }, "geometry": { "type": "Point", "coordinates": [ -1.619791768936816, 53.869337587487699 ] } },
{ "type": "Feature", "properties": { "visible_points": 10, "total_points": 21, "visibility_pct": 47.619047619047613 }, "geometry": { "type": "Point", "coordinates": [ -1.619489251912646, 53.869156875025801 ] } },
{ "type": "Feature", "properties": { "visible_points": 7, "total_points": 21, "visibility_pct": 33.333333333333329 }, "geometry": { "type": "Point", "coordinates": [ -1.619487624821742, 53.869336626827362 ] } },
{ "type": "Feature", "properties": { "visible_points": 9, "total_points": 21, "visibility_pct": 42.857142857142854 }, "geometry": { "type": "Point", "coordinates": [ -1.619485997713245, 53.86951637862348 ] } },
{ "type": "Feature", "properties": { "visible_points": 10, "total_points": 21, "visibility_pct": 47.619047619047613 }, "geometry": { "type": "Point", "coordinates": [ -1.619484370587156, 53.869696130414155 ] } },
{ "type": "Feature", "properties": { "visible_points": 5, "total_points": 21, "visibility_pct": 23.809523809523807 }, "geometry": { "type": "Point", "coordinates": [ -1.61918510909995, 53.869155913602562 ] } },
{ "type": "Feature", "properties": { "visible_points": 9, "total_points": 21, "visibility_pct": 42.857142857142854 }, "geometry": { "type": "Point", "coordinates": [ -1.619183480724212, 53.869335665396292 ] } },
{ "type": "Feature", "properties": { "visible_points": 11, "total_points": 21, "visibility_pct": 52.380952380952387 }, "geometry": { "type": "Point", "coordinates": [ -1.619181852330867, 53.86951541718458 ] } },
{ "type": "Feature", "properties": { "visible_points": 10, "total_points": 21, "visibility_pct": 47.619047619047613 }, "geometry": { "type": "Point", "coordinates": [ -1.619180223919916, 53.869695168967411 ] } },
{ "type": "Feature", "properties": { "visible_points": 6, "total_points": 21, "visibility_pct": 28.571428571428569 }, "geometry": { "type": "Point", "coordinates": [ -1.618880966304813, 53.869154951408611 ] } },
{ "type": "Feature", "properties": { "visible_points": 0, "total_points": 21, "visibility_pct": 0.0 }, "geometry": { "type": "Point", "coordinates": [ -1.618879336644241, 53.86933470319449 ] } },
{ "type": "Feature", "properties": { "visible_points": 11, "total_points": 21, "visibility_pct": 52.380952380952387 }, "geometry": { "type": "Point", "coordinates": [ -1.618877706966049, 53.869514454974933 ] } },
{ "type": "Feature", "properties": { "visible_points": 8, "total_points": 21, "visibility_pct": 38.095238095238095 }, "geometry": { "type": "Point", "coordinates": [ -1.618876077270236, 53.869694206749926 ] } },
{ "type": "Feature", "properties": { "visible_points": 4, "total_points": 21, "visibility_pct": 19.047619047619047 }, "geometry": { "type": "Point", "coordinates": [ -1.618576823527249, 53.869153988443927 ] } },
{ "type": "Feature", "properties": { "visible_points": 3, "total_points": 21, "visibility_pct": 14.285714285714285 }, "geometry": { "type": "Point", "coordinates": [ -1.618575192581844, 53.869333740221961 ] } },
{ "type": "Feature", "properties": { "visible_points": 9, "total_points": 21, "visibility_pct": 42.857142857142854 }, "geometry": { "type": "Point", "coordinates": [ -1.618573561618804, 53.869513491994553 ] } },
{ "type": "Feature", "properties": { "visible_points": 5, "total_points": 21, "visibility_pct": 23.809523809523807 }, "geometry": { "type": "Point", "coordinates": [ -1.618571930638129, 53.869693243761695 ] } },
{ "type": "Feature", "properties": { "visible_points": 0, "total_points": 20, "visibility_pct": 0.0 }, "geometry": { "type": "Point", "coordinates": [ -1.618272680767271, 53.869153024708531 ] } },
{ "type": "Feature", "properties": { "visible_points": 8, "total_points": 20, "visibility_pct": 40.0 }, "geometry": { "type": "Point", "coordinates": [ -1.618271048537033, 53.8693327764787 ] } },
{ "type": "Feature", "properties": { "visible_points": 8, "total_points": 19, "visibility_pct": 42.105263157894733 }, "geometry": { "type": "Point", "coordinates": [ -1.618269416289146, 53.869512528243426 ] } },
{ "type": "Feature", "properties": { "visible_points": 2, "total_points": 19, "visibility_pct": 10.526315789473683 }, "geometry": { "type": "Point", "coordinates": [ -1.618267784023611, 53.869692280002724 ] } }
]
}
