{
"type": "FeatureCollection",
"name": "Leeds_Rowland_Road_Park_OSM_trees",
"crs": { "type": "name", "properties": { "name": "urn:ogc:def:crs:OGC:1.3:CRS84" } },
"features": [
{ "type": "Feature", "properties": { "Park Feature": "Tree" }, "geometry": { "type": "Point", "coordinates": [ -1.558479, 53.7774296 ] } }
]
}
