{
"type": "FeatureCollection",
"name": "Leeds_Rowland_Road_Park_summer_vga",
"crs": { "type": "name", "properties": { "name": "urn:ogc:def:crs:OGC:1.3:CRS84" } },
"features": [
{ "type": "Feature", "properties": { "visible_points": 2, "total_points": 3, "visibility_pct": 66.666666666666657 }, "geometry": { "type": "Point", "coordinates": [ -1.546967347265309, 53.776479823251172 ] } },
{ "type": "Feature", "properties": { "visible_points": 0, "total_points": 3, "visibility_pct": 0.0 }, "geometry": { "type": "Point", "coordinates": [ -1.546965415745897, 53.77665957627535 ] } },
{ "type": "Feature", "properties": { "visible_points": 2, "total_points": 3, "visibility_pct": 66.666666666666657 }, "geometry": { "type": "Point", "coordinates": [ -1.546663878018309, 53.776478679002345 ] } },
{ "type": "Feature", "properties": { "visible_points": 2, "total_points": 3, "visibility_pct": 66.666666666666657 }, "geometry": { "type": "Point", "coordinates": [ -1.546661945133732, 53.776658431992843 ] } }
]
}
