{
"type": "FeatureCollection",
"name": "Bradford_Pheasant_Wood_summer_vga",
"crs": { "type": "name", "properties": { "name": "urn:ogc:def:crs:OGC:1.3:CRS84" } },
"features": [
{ "type": "Feature", "properties": { "visible_points": 0, "total_points": 2, "visibility_pct": 0.0 }, "geometry": { "type": "Point", "coordinates": [ -1.959644417460344, 53.814742419831362 ] } },
{ "type": "Feature", "properties": { "visible_points": 0, "total_points": 2, "visibility_pct": 0.0 }, "geometry": { "type": "Point", "coordinates": [ -1.959644249012473, 53.814922176243051 ] } },
{ "type": "Feature", "properties": { "visible_points": 0, "total_points": 2, "visibility_pct": 0.0 }, "geometry": { "type": "Point", "coordinates": [ -1.959340831729952, 53.814562561215219 ] } }
]
}
