{
"type": "FeatureCollection",
"name": "Bradford_Hunter_Hill_Plantation_external_entrances",
"crs": { "type": "name", "properties": { "name": "urn:ogc:def:crs:OGC:1.3:CRS84" } },
"features": [
{ "type": "Feature", "properties": { "id": null, "access_type": "vehicle", "Park Name": "Hunter Hill Plantation", "Park Segment Name": "Hunter Hill Plantation", "source": "calculated", "highway_type": "tertiary" }, "geometry": { "type": "Point", "coordinates": [ -1.890561299999021, 53.838877599999897 ] } },
{ "type": "Feature", "properties": { "id": null, "access_type": "vehicle", "Park Name": "Hunter Hill Plantation", "Park Segment Name": "Hunter Hill Plantation", "source": "calculated", "highway_type": "tertiary" }, "geometry": { "type": "Point", "coordinates": [ -1.891124396691321, 53.83915944040826 ] } },
{ "type": "Feature", "properties": { "id": null, "access_type": "horse", "Park Name": "Hunter Hill Plantation", "Park Segment Name": "Hunter Hill Plantation", "source": "calculated", "highway_type": "bridleway" }, "geometry": { "type": "Point", "coordinates": [ -1.889612285073035, 53.836929466399233 ] } },
{ "type": "Feature", "properties": { "id": null, "access_type": "horse", "Park Name": "Hunter Hill Plantation", "Park Segment Name": "Hunter Hill Plantation", "source": "calculated", "highway_type": "bridleway" }, "geometry": { "type": "Point", "coordinates": [ -1.890142564085235, 53.836805381687427 ] } },
{ "type": "Feature", "properties": { "id": null, "access_type": "horse", "Park Name": "Hunter Hill Plantation", "Park Segment Name": "Hunter Hill Plantation", "source": "calculated", "highway_type": "bridleway" }, "geometry": { "type": "Point", "coordinates": [ -1.891479030271059, 53.836591401121396 ] } },
{ "type": "Feature", "properties": { "id": null, "access_type": "horse", "Park Name": "Hunter Hill Plantation", "Park Segment Name": "Hunter Hill Plantation", "source": "calculated", "highway_type": "bridleway" }, "geometry": { "type": "Point", "coordinates": [ -1.888913183803691, 53.83710762607209 ] } },
{ "type": "Feature", "properties": { "id": null, "access_type": "vehicle", "Park Name": "Royd Wood", "Park Segment Name": "Royd Wood", "source": "calculated", "highway_type": "service" }, "geometry": { "type": "Point", "coordinates": [ -1.891443942127955, 53.829886035339783 ] } },
{ "type": "Feature", "properties": { "id": null, "access_type": "vehicle", "Park Name": "Royd Wood", "Park Segment Name": "Royd Wood", "source": "calculated", "highway_type": "service" }, "geometry": { "type": "Point", "coordinates": [ -1.89109684564812, 53.830515946124841 ] } },
{ "type": "Feature", "properties": { "id": null, "access_type": "vehicle", "Park Name": "Royd Wood", "Park Segment Name": "Royd Wood", "source": "calculated", "highway_type": "service" }, "geometry": { "type": "Point", "coordinates": [ -1.890996783422877, 53.830487420343502 ] } },
{ "type": "Feature", "properties": { "id": null, "access_type": "vehicle", "Park Name": "Royd Wood", "Park Segment Name": "Royd Wood", "source": "calculated", "highway_type": "service" }, "geometry": { "type": "Point", "coordinates": [ -1.892032238289454, 53.830852015335367 ] } },
{ "type": "Feature", "properties": { "id": null, "access_type": "vehicle", "Park Name": "Ryecroft Plantation", "Park Segment Name": "Ryecroft Plantation", "source": "calculated", "highway_type": "tertiary" }, "geometry": { "type": "Point", "coordinates": [ -1.881127590790163, 53.838801431662453 ] } },
{ "type": "Feature", "properties": { "id": null, "access_type": "vehicle", "Park Name": "Ryecroft Plantation", "Park Segment Name": "Ryecroft Plantation", "source": "calculated", "highway_type": "tertiary" }, "geometry": { "type": "Point", "coordinates": [ -1.881198237401723, 53.838790070260259 ] } },
{ "type": "Feature", "properties": { "id": null, "access_type": "foot", "Park Name": "Ryecroft Plantation", "Park Segment Name": "Ryecroft Plantation", "source": "calculated", "highway_type": "footway" }, "geometry": { "type": "Point", "coordinates": [ -1.880799610446971, 53.83886007506198 ] } },
{ "type": "Feature", "properties": { "id": null, "access_type": "foot", "Park Name": "Ryecroft Plantation", "Park Segment Name": "Ryecroft Plantation", "source": "calculated", "highway_type": "footway" }, "geometry": { "type": "Point", "coordinates": [ -1.883413764460384, 53.83802349855948 ] } }
]
}
