{
"type": "FeatureCollection",
"name": "Bradford_Spring_Mill_Street_Recreation_Ground_summer_vga",
"crs": { "type": "name", "properties": { "name": "urn:ogc:def:crs:OGC:1.3:CRS84" } },
"features": [
{ "type": "Feature", "properties": { "visible_points": 7, "total_points": 8, "visibility_pct": 87.5 }, "geometry": { "type": "Point", "coordinates": [ -1.751591420913705, 53.780467116954647 ] } },
{ "type": "Feature", "properties": { "visible_points": 5, "total_points": 8, "visibility_pct": 62.5 }, "geometry": { "type": "Point", "coordinates": [ -1.751590362196713, 53.780646873586626 ] } },
{ "type": "Feature", "properties": { "visible_points": 7, "total_points": 8, "visibility_pct": 87.5 }, "geometry": { "type": "Point", "coordinates": [ -1.751287917495393, 53.780466489968497 ] } },
{ "type": "Feature", "properties": { "visible_points": 7, "total_points": 8, "visibility_pct": 87.5 }, "geometry": { "type": "Point", "coordinates": [ -1.751286857504775, 53.780646246608569 ] } },
{ "type": "Feature", "properties": { "visible_points": 7, "total_points": 8, "visibility_pct": 87.5 }, "geometry": { "type": "Point", "coordinates": [ -1.750984414190699, 53.78046586229582 ] } },
{ "type": "Feature", "properties": { "visible_points": 6, "total_points": 8, "visibility_pct": 75.0 }, "geometry": { "type": "Point", "coordinates": [ -1.750983352929526, 53.78064561894378 ] } },
{ "type": "Feature", "properties": { "visible_points": 7, "total_points": 8, "visibility_pct": 87.5 }, "geometry": { "type": "Point", "coordinates": [ -1.750680910897389, 53.780465233854777 ] } },
{ "type": "Feature", "properties": { "visible_points": 6, "total_points": 8, "visibility_pct": 75.0 }, "geometry": { "type": "Point", "coordinates": [ -1.750679848365663, 53.780644990510609 ] } },
{ "type": "Feature", "properties": { "visible_points": 0, "total_points": 8, "visibility_pct": 0.0 }, "geometry": { "type": "Point", "coordinates": [ -1.750678785822498, 53.780824747161112 ] } }
]
}
