{
"type": "FeatureCollection",
"name": "Kirklees_Heckmondwike_Green_summer_vga",
"crs": { "type": "name", "properties": { "name": "urn:ogc:def:crs:OGC:1.3:CRS84" } },
"features": [
{ "type": "Feature", "properties": { "visible_points": 8, "total_points": 9, "visibility_pct": 88.888888888888886 }, "geometry": { "type": "Point", "coordinates": [ -1.677111343958389, 53.708025981113749 ] } },
{ "type": "Feature", "properties": { "visible_points": 8, "total_points": 9, "visibility_pct": 88.888888888888886 }, "geometry": { "type": "Point", "coordinates": [ -1.677109970674731, 53.708205743103569 ] } },
{ "type": "Feature", "properties": { "visible_points": 7, "total_points": 9, "visibility_pct": 77.777777777777786 }, "geometry": { "type": "Point", "coordinates": [ -1.677108597375103, 53.708385505088401 ] } },
{ "type": "Feature", "properties": { "visible_points": 9, "total_points": 9, "visibility_pct": 100.0 }, "geometry": { "type": "Point", "coordinates": [ -1.676809742182669, 53.707845398256424 ] } },
{ "type": "Feature", "properties": { "visible_points": 9, "total_points": 9, "visibility_pct": 100.0 }, "geometry": { "type": "Point", "coordinates": [ -1.676808367514382, 53.708025160293069 ] } },
{ "type": "Feature", "properties": { "visible_points": 9, "total_points": 9, "visibility_pct": 100.0 }, "geometry": { "type": "Point", "coordinates": [ -1.67680699283011, 53.708204922324711 ] } },
{ "type": "Feature", "properties": { "visible_points": 9, "total_points": 9, "visibility_pct": 100.0 }, "geometry": { "type": "Point", "coordinates": [ -1.676805618129852, 53.708384684351351 ] } },
{ "type": "Feature", "properties": { "visible_points": 8, "total_points": 9, "visibility_pct": 88.888888888888886 }, "geometry": { "type": "Point", "coordinates": [ -1.676506767155207, 53.707844576627238 ] } },
{ "type": "Feature", "properties": { "visible_points": 8, "total_points": 9, "visibility_pct": 88.888888888888886 }, "geometry": { "type": "Point", "coordinates": [ -1.676505391086321, 53.708024338705698 ] } },
{ "type": "Feature", "properties": { "visible_points": 9, "total_points": 9, "visibility_pct": 100.0 }, "geometry": { "type": "Point", "coordinates": [ -1.676203792143705, 53.707843754231362 ] } }
]
}
