{
"type": "FeatureCollection",
"name": "Bradford_Cottingley_Village_Green_summer_vga",
"crs": { "type": "name", "properties": { "name": "urn:ogc:def:crs:OGC:1.3:CRS84" } },
"features": [
{ "type": "Feature", "properties": { "visible_points": 1, "total_points": 1, "visibility_pct": 100.0 }, "geometry": { "type": "Point", "coordinates": [ -1.828871123597764, 53.829599243032391 ] } },
{ "type": "Feature", "properties": { "visible_points": 1, "total_points": 1, "visibility_pct": 100.0 }, "geometry": { "type": "Point", "coordinates": [ -1.828567263938321, 53.829598810977764 ] } }
]
}
