{
"type": "FeatureCollection",
"name": "Leeds_Calverley_Wood_external_entrances",
"crs": { "type": "name", "properties": { "name": "urn:ogc:def:crs:OGC:1.3:CRS84" } },
"features": [
{ "type": "Feature", "properties": { "id": null, "access_type": "foot", "Park Name": "Bill Wood", "Park Segment Name": "Bill Wood", "source": "calculated", "highway_type": "path" }, "geometry": { "type": "Point", "coordinates": [ -1.707174124958626, 53.829078130707437 ] } },
{ "type": "Feature", "properties": { "id": null, "access_type": "foot", "Park Name": "Bill Wood", "Park Segment Name": "Bill Wood", "source": "calculated", "highway_type": "path" }, "geometry": { "type": "Point", "coordinates": [ -1.707499289171339, 53.82861869244816 ] } },
{ "type": "Feature", "properties": { "id": null, "access_type": "foot", "Park Name": "Bill Wood", "Park Segment Name": "Bill Wood", "source": "calculated", "highway_type": "path" }, "geometry": { "type": "Point", "coordinates": [ -1.704232592679034, 53.82682528098514 ] } },
{ "type": "Feature", "properties": { "id": null, "access_type": "foot", "Park Name": "Bill Wood", "Park Segment Name": "Bill Wood", "source": "calculated", "highway_type": "path" }, "geometry": { "type": "Point", "coordinates": [ -1.70378169538557, 53.826754830118766 ] } },
{ "type": "Feature", "properties": { "id": null, "access_type": "horse", "Park Name": "Bill Wood", "Park Segment Name": "Bill Wood", "source": "calculated", "highway_type": "bridleway" }, "geometry": { "type": "Point", "coordinates": [ -1.704371610206622, 53.827041238470159 ] } },
{ "type": "Feature", "properties": { "id": null, "access_type": "vehicle", "Park Name": "Bill Wood", "Park Segment Name": "Bill Wood", "source": "calculated", "highway_type": "track" }, "geometry": { "type": "Point", "coordinates": [ -1.706029680921749, 53.827973256772566 ] } },
{ "type": "Feature", "properties": { "id": null, "access_type": "foot", "Park Name": "Bill Wood", "Park Segment Name": "Bill Wood", "source": "calculated", "highway_type": "footway" }, "geometry": { "type": "Point", "coordinates": [ -1.705220356334532, 53.827666208161752 ] } },
{ "type": "Feature", "properties": { "id": null, "access_type": "vehicle", "Park Name": "Bill Wood", "Park Segment Name": "Bill Wood", "source": "calculated", "highway_type": "track" }, "geometry": { "type": "Point", "coordinates": [ -1.707016268867937, 53.82888464104294 ] } }
]
}
