{
"type": "FeatureCollection",
"name": "Leeds_High_Royds_Woodland_Nature_Reserve_summer_vga",
"crs": { "type": "name", "properties": { "name": "urn:ogc:def:crs:OGC:1.3:CRS84" } },
"features": [
{ "type": "Feature", "properties": { "visible_points": 0, "total_points": 15, "visibility_pct": 0.0 }, "geometry": { "type": "Point", "coordinates": [ -1.727403382022546, 53.88701818916401 ] } },
{ "type": "Feature", "properties": { "visible_points": 0, "total_points": 14, "visibility_pct": 0.0 }, "geometry": { "type": "Point", "coordinates": [ -1.72740222265021, 53.887197946726829 ] } },
{ "type": "Feature", "properties": { "visible_points": 0, "total_points": 13, "visibility_pct": 0.0 }, "geometry": { "type": "Point", "coordinates": [ -1.72740106326556, 53.88737770428439 ] } },
{ "type": "Feature", "properties": { "visible_points": 0, "total_points": 17, "visibility_pct": 0.0 }, "geometry": { "type": "Point", "coordinates": [ -1.727101435271325, 53.886657984857194 ] } },
{ "type": "Feature", "properties": { "visible_points": 0, "total_points": 17, "visibility_pct": 0.0 }, "geometry": { "type": "Point", "coordinates": [ -1.727100274678893, 53.886837742445287 ] } },
{ "type": "Feature", "properties": { "visible_points": 0, "total_points": 16, "visibility_pct": 0.0 }, "geometry": { "type": "Point", "coordinates": [ -1.727099114074132, 53.887017500028101 ] } },
{ "type": "Feature", "properties": { "visible_points": 0, "total_points": 15, "visibility_pct": 0.0 }, "geometry": { "type": "Point", "coordinates": [ -1.727097953457043, 53.887197257605663 ] } },
{ "type": "Feature", "properties": { "visible_points": 0, "total_points": 14, "visibility_pct": 0.0 }, "geometry": { "type": "Point", "coordinates": [ -1.727096792827625, 53.887377015177954 ] } },
{ "type": "Feature", "properties": { "visible_points": 0, "total_points": 13, "visibility_pct": 0.0 }, "geometry": { "type": "Point", "coordinates": [ -1.727095632185879, 53.887556772744979 ] } },
{ "type": "Feature", "properties": { "visible_points": 2, "total_points": 17, "visibility_pct": 11.76470588235294 }, "geometry": { "type": "Point", "coordinates": [ -1.726794846137975, 53.887016810120762 ] } },
{ "type": "Feature", "properties": { "visible_points": 2, "total_points": 15, "visibility_pct": 13.333333333333334 }, "geometry": { "type": "Point", "coordinates": [ -1.726793684276132, 53.887196567713055 ] } },
{ "type": "Feature", "properties": { "visible_points": 0, "total_points": 14, "visibility_pct": 0.0 }, "geometry": { "type": "Point", "coordinates": [ -1.726792522401947, 53.887376325300082 ] } },
{ "type": "Feature", "properties": { "visible_points": 0, "total_points": 17, "visibility_pct": 0.0 }, "geometry": { "type": "Point", "coordinates": [ -1.726491741308327, 53.886836361829715 ] } },
{ "type": "Feature", "properties": { "visible_points": 2, "total_points": 17, "visibility_pct": 11.76470588235294 }, "geometry": { "type": "Point", "coordinates": [ -1.726490578214087, 53.887016119441988 ] } },
{ "type": "Feature", "properties": { "visible_points": 0, "total_points": 9, "visibility_pct": 0.0 }, "geometry": { "type": "Point", "coordinates": [ -1.726190967584187, 53.886296397452199 ] } },
{ "type": "Feature", "properties": { "visible_points": 0, "total_points": 12, "visibility_pct": 0.0 }, "geometry": { "type": "Point", "coordinates": [ -1.726189803282315, 53.886476155094996 ] } },
{ "type": "Feature", "properties": { "visible_points": 0, "total_points": 15, "visibility_pct": 0.0 }, "geometry": { "type": "Point", "coordinates": [ -1.726188638968073, 53.886655912732529 ] } },
{ "type": "Feature", "properties": { "visible_points": 0, "total_points": 8, "visibility_pct": 0.0 }, "geometry": { "type": "Point", "coordinates": [ -1.725886704663754, 53.88629570517169 ] } }
]
}
