{
"type": "FeatureCollection",
"name": "Bradford_Brighton_Wood_external_entrances",
"crs": { "type": "name", "properties": { "name": "urn:ogc:def:crs:OGC:1.3:CRS84" } },
"features": [
{ "type": "Feature", "properties": { "id": null, "access_type": "foot", "Park Name": "Currer Wood", "Park Segment Name": "Currer Wood", "source": "calculated", "highway_type": "footway" }, "geometry": { "type": "Point", "coordinates": [ -1.95801760637292, 53.890581420143349 ] } }
]
}
