{
"type": "FeatureCollection",
"name": "Leeds_Sledmere_Green_summer_vga",
"crs": { "type": "name", "properties": { "name": "urn:ogc:def:crs:OGC:1.3:CRS84" } },
"features": [
{ "type": "Feature", "properties": { "visible_points": 2, "total_points": 3, "visibility_pct": 66.666666666666657 }, "geometry": { "type": "Point", "coordinates": [ -1.449668728147182, 53.825757507477419 ] } },
{ "type": "Feature", "properties": { "visible_points": 4, "total_points": 4, "visibility_pct": 100.0 }, "geometry": { "type": "Point", "coordinates": [ -1.449063439782754, 53.825574971132134 ] } },
{ "type": "Feature", "properties": { "visible_points": 3, "total_points": 4, "visibility_pct": 75.0 }, "geometry": { "type": "Point", "coordinates": [ -1.448759620316987, 53.825573578131078 ] } },
{ "type": "Feature", "properties": { "visible_points": 4, "total_points": 4, "visibility_pct": 100.0 }, "geometry": { "type": "Point", "coordinates": [ -1.448458156809828, 53.82539243175767 ] } },
{ "type": "Feature", "properties": { "visible_points": 3, "total_points": 3, "visibility_pct": 100.0 }, "geometry": { "type": "Point", "coordinates": [ -1.448154338724558, 53.825391037231284 ] } }
]
}
