{
"type": "FeatureCollection",
"name": "Bradford_Willy_Halls_Wood_summer_vga",
"crs": { "type": "name", "properties": { "name": "urn:ogc:def:crs:OGC:1.3:CRS84" } },
"features": [
{ "type": "Feature", "properties": { "visible_points": 0, "total_points": 5, "visibility_pct": 0.0 }, "geometry": { "type": "Point", "coordinates": [ -1.825042757096837, 53.915384370391919 ] } },
{ "type": "Feature", "properties": { "visible_points": 0, "total_points": 7, "visibility_pct": 0.0 }, "geometry": { "type": "Point", "coordinates": [ -1.825042008343946, 53.915564124524998 ] } },
{ "type": "Feature", "properties": { "visible_points": 0, "total_points": 7, "visibility_pct": 0.0 }, "geometry": { "type": "Point", "coordinates": [ -1.825041259582725, 53.915743878652613 ] } },
{ "type": "Feature", "properties": { "visible_points": 0, "total_points": 7, "visibility_pct": 0.0 }, "geometry": { "type": "Point", "coordinates": [ -1.825040510813172, 53.915923632774756 ] } },
{ "type": "Feature", "properties": { "visible_points": 0, "total_points": 7, "visibility_pct": 0.0 }, "geometry": { "type": "Point", "coordinates": [ -1.825039762035289, 53.916103386891429 ] } },
{ "type": "Feature", "properties": { "visible_points": 0, "total_points": 7, "visibility_pct": 0.0 }, "geometry": { "type": "Point", "coordinates": [ -1.825039013249075, 53.916283141002644 ] } },
{ "type": "Feature", "properties": { "visible_points": 0, "total_points": 6, "visibility_pct": 0.0 }, "geometry": { "type": "Point", "coordinates": [ -1.825038264454529, 53.916462895108381 ] } },
{ "type": "Feature", "properties": { "visible_points": 0, "total_points": 6, "visibility_pct": 0.0 }, "geometry": { "type": "Point", "coordinates": [ -1.82473452190478, 53.916282698740666 ] } }
]
}
