{
"type": "FeatureCollection",
"name": "Wakefield_Dale_Park_summer_vga",
"crs": { "type": "name", "properties": { "name": "urn:ogc:def:crs:OGC:1.3:CRS84" } },
"features": [
{ "type": "Feature", "properties": { "visible_points": 0, "total_points": 5, "visibility_pct": 0.0 }, "geometry": { "type": "Point", "coordinates": [ -1.30918576736974, 53.690670442780828 ] } },
{ "type": "Feature", "properties": { "visible_points": 0, "total_points": 5, "visibility_pct": 0.0 }, "geometry": { "type": "Point", "coordinates": [ -1.309182815944386, 53.690850186445665 ] } },
{ "type": "Feature", "properties": { "visible_points": 0, "total_points": 5, "visibility_pct": 0.0 }, "geometry": { "type": "Point", "coordinates": [ -1.308879966603439, 53.690848439208509 ] } },
{ "type": "Feature", "properties": { "visible_points": 0, "total_points": 5, "visibility_pct": 0.0 }, "geometry": { "type": "Point", "coordinates": [ -1.308877013854636, 53.6910281828564 ] } },
{ "type": "Feature", "properties": { "visible_points": 0, "total_points": 5, "visibility_pct": 0.0 }, "geometry": { "type": "Point", "coordinates": [ -1.308577117294472, 53.690846691205721 ] } },
{ "type": "Feature", "properties": { "visible_points": 0, "total_points": 5, "visibility_pct": 0.0 }, "geometry": { "type": "Point", "coordinates": [ -1.308574163254179, 53.691026434842179 ] } }
]
}
