{
"type": "FeatureCollection",
"name": "Bradford_Lodge_Hill_Wood_park_street_lights",
"crs": { "type": "name", "properties": { "name": "urn:ogc:def:crs:OGC:1.3:CRS84" } },
"features": [
{ "type": "Feature", "properties": { "Park Feature": "Street Light" }, "geometry": { "type": "Point", "coordinates": [ -1.919858971970842, 53.884584099425567 ] } }
]
}
