{
"type": "FeatureCollection",
"name": "Calderdale_Callis_Wood_OSM_benches_picnic",
"crs": { "type": "name", "properties": { "name": "urn:ogc:def:crs:OGC:1.3:CRS84" } },
"features": [
{ "type": "Feature", "properties": { "Park Feature": "Bench" }, "geometry": { "type": "Point", "coordinates": [ -2.0136885, 53.7401222 ] } }
]
}
