{
"type": "FeatureCollection",
"name": "Bradford_Branshaw_Plantation_OSM_benches_picnic",
"crs": { "type": "name", "properties": { "name": "urn:ogc:def:crs:OGC:1.3:CRS84" } },
"features": [
{ "type": "Feature", "properties": { "Park Feature": "Picnic Table" }, "geometry": { "type": "Point", "coordinates": [ -1.9489137, 53.8465733 ] } }
]
}
