{
"type": "FeatureCollection",
"name": "Kirklees_Little_Spring_summer_vga",
"crs": { "type": "name", "properties": { "name": "urn:ogc:def:crs:OGC:1.3:CRS84" } },
"features": [
{ "type": "Feature", "properties": { "visible_points": 2, "total_points": 5, "visibility_pct": 40.0 }, "geometry": { "type": "Point", "coordinates": [ -1.676736954872709, 53.614574227993039 ] } },
{ "type": "Feature", "properties": { "visible_points": 2, "total_points": 5, "visibility_pct": 40.0 }, "geometry": { "type": "Point", "coordinates": [ -1.676735584362547, 53.614753986932413 ] } },
{ "type": "Feature", "properties": { "visible_points": 2, "total_points": 5, "visibility_pct": 40.0 }, "geometry": { "type": "Point", "coordinates": [ -1.676734213837416, 53.614933745866416 ] } },
{ "type": "Feature", "properties": { "visible_points": 0, "total_points": 5, "visibility_pct": 0.0 }, "geometry": { "type": "Point", "coordinates": [ -1.676732843297316, 53.615113504795005 ] } },
{ "type": "Feature", "properties": { "visible_points": 1, "total_points": 5, "visibility_pct": 20.0 }, "geometry": { "type": "Point", "coordinates": [ -1.676731472742246, 53.615293263718208 ] } },
{ "type": "Feature", "properties": { "visible_points": 1, "total_points": 5, "visibility_pct": 20.0 }, "geometry": { "type": "Point", "coordinates": [ -1.676730102172206, 53.615473022636017 ] } }
]
}
