{
"type": "FeatureCollection",
"name": "Kirklees_Biggin_Shrogg_summer_vga",
"crs": { "type": "name", "properties": { "name": "urn:ogc:def:crs:OGC:1.3:CRS84" } },
"features": [
{ "type": "Feature", "properties": { "visible_points": 0, "total_points": 9, "visibility_pct": 0.0 }, "geometry": { "type": "Point", "coordinates": [ -1.750983046688157, 53.584124837848719 ] } },
{ "type": "Feature", "properties": { "visible_points": 0, "total_points": 9, "visibility_pct": 0.0 }, "geometry": { "type": "Point", "coordinates": [ -1.750981993980197, 53.584304600739983 ] } },
{ "type": "Feature", "properties": { "visible_points": 0, "total_points": 9, "visibility_pct": 0.0 }, "geometry": { "type": "Point", "coordinates": [ -1.750682008232636, 53.583944448007387 ] } },
{ "type": "Feature", "properties": { "visible_points": 0, "total_points": 9, "visibility_pct": 0.0 }, "geometry": { "type": "Point", "coordinates": [ -1.75068095424859, 53.584124210901152 ] } },
{ "type": "Feature", "properties": { "visible_points": 0, "total_points": 9, "visibility_pct": 0.0 }, "geometry": { "type": "Point", "coordinates": [ -1.750679900253009, 53.584303973789503 ] } },
{ "type": "Feature", "properties": { "visible_points": 1, "total_points": 9, "visibility_pct": 11.111111111111111 }, "geometry": { "type": "Point", "coordinates": [ -1.75037991709217, 53.583943820299915 ] } },
{ "type": "Feature", "properties": { "visible_points": 0, "total_points": 9, "visibility_pct": 0.0 }, "geometry": { "type": "Point", "coordinates": [ -1.750378861820517, 53.58412358319076 ] } },
{ "type": "Feature", "properties": { "visible_points": 0, "total_points": 9, "visibility_pct": 0.0 }, "geometry": { "type": "Point", "coordinates": [ -1.750377806537314, 53.584303346076197 ] } },
{ "type": "Feature", "properties": { "visible_points": 2, "total_points": 9, "visibility_pct": 22.222222222222221 }, "geometry": { "type": "Point", "coordinates": [ -1.750077825963209, 53.583943191829597 ] } },
{ "type": "Feature", "properties": { "visible_points": 1, "total_points": 9, "visibility_pct": 11.111111111111111 }, "geometry": { "type": "Point", "coordinates": [ -1.750076769403949, 53.584122954717536 ] } }
]
}
