{
"type": "FeatureCollection",
"name": "Leeds_Ackroyds_Wood_OSM_trees",
"crs": { "type": "name", "properties": { "name": "urn:ogc:def:crs:OGC:1.3:CRS84" } },
"features": [
{ "type": "Feature", "properties": { "Park Feature": "Tree" }, "geometry": { "type": "Point", "coordinates": [ -1.698135, 53.8971472 ] } },
{ "type": "Feature", "properties": { "Park Feature": "Tree" }, "geometry": { "type": "Point", "coordinates": [ -1.6982495, 53.8971648 ] } },
{ "type": "Feature", "properties": { "Park Feature": "Tree" }, "geometry": { "type": "Point", "coordinates": [ -1.6982701, 53.8972538 ] } },
{ "type": "Feature", "properties": { "Park Feature": "Tree" }, "geometry": { "type": "Point", "coordinates": [ -1.6981373, 53.8972687 ] } },
{ "type": "Feature", "properties": { "Park Feature": "Tree" }, "geometry": { "type": "Point", "coordinates": [ -1.6980113, 53.8972187 ] } },
{ "type": "Feature", "properties": { "Park Feature": "Tree" }, "geometry": { "type": "Point", "coordinates": [ -1.6979495, 53.8972754 ] } },
{ "type": "Feature", "properties": { "Park Feature": "Tree" }, "geometry": { "type": "Point", "coordinates": [ -1.6984121, 53.8972187 ] } },
{ "type": "Feature", "properties": { "Park Feature": "Tree" }, "geometry": { "type": "Point", "coordinates": [ -1.6982403, 53.8970622 ] } },
{ "type": "Feature", "properties": { "Park Feature": "Tree" }, "geometry": { "type": "Point", "coordinates": [ -1.6982403, 53.8969731 ] } },
{ "type": "Feature", "properties": { "Park Feature": "Tree" }, "geometry": { "type": "Point", "coordinates": [ -1.6983617, 53.8969785 ] } },
{ "type": "Feature", "properties": { "Park Feature": "Tree" }, "geometry": { "type": "Point", "coordinates": [ -1.6983571, 53.8969448 ] } },
{ "type": "Feature", "properties": { "Park Feature": "Tree" }, "geometry": { "type": "Point", "coordinates": [ -1.697109, 53.8973186 ] } },
{ "type": "Feature", "properties": { "Park Feature": "Tree" }, "geometry": { "type": "Point", "coordinates": [ -1.6969464, 53.8973645 ] } },
{ "type": "Feature", "properties": { "Park Feature": "Tree" }, "geometry": { "type": "Point", "coordinates": [ -1.6969487, 53.8972862 ] } },
{ "type": "Feature", "properties": { "Park Feature": "Tree" }, "geometry": { "type": "Point", "coordinates": [ -1.6963602, 53.8971445 ] } },
{ "type": "Feature", "properties": { "Park Feature": "Tree" }, "geometry": { "type": "Point", "coordinates": [ -1.6966556, 53.8971782 ] } },
{ "type": "Feature", "properties": { "Park Feature": "Tree" }, "geometry": { "type": "Point", "coordinates": [ -1.6962319, 53.8961365 ] } },
{ "type": "Feature", "properties": { "Park Feature": "Tree" }, "geometry": { "type": "Point", "coordinates": [ -1.6965571, 53.8960866 ] } },
{ "type": "Feature", "properties": { "Park Feature": "Tree" }, "geometry": { "type": "Point", "coordinates": [ -1.6964174, 53.8963187 ] } },
{ "type": "Feature", "properties": { "Park Feature": "Tree" }, "geometry": { "type": "Point", "coordinates": [ -1.696809, 53.896042 ] } },
{ "type": "Feature", "properties": { "Park Feature": "Tree" }, "geometry": { "type": "Point", "coordinates": [ -1.6980704, 53.8969609 ] } },
{ "type": "Feature", "properties": { "Park Feature": "Tree" }, "geometry": { "type": "Point", "coordinates": [ -1.6980706, 53.8969404 ] } },
{ "type": "Feature", "properties": { "Park Feature": "Tree" }, "geometry": { "type": "Point", "coordinates": [ -1.698072, 53.8969176 ] } },
{ "type": "Feature", "properties": { "Park Feature": "Tree" }, "geometry": { "type": "Point", "coordinates": [ -1.6980713, 53.8968915 ] } }
]
}
