{
"type": "FeatureCollection",
"name": "Kirklees_Round_Hill_Wood_summer_vga",
"crs": { "type": "name", "properties": { "name": "urn:ogc:def:crs:OGC:1.3:CRS84" } },
"features": [
{ "type": "Feature", "properties": { "visible_points": 0, "total_points": 22, "visibility_pct": 0.0 }, "geometry": { "type": "Point", "coordinates": [ -1.624744988646203, 53.643485517148036 ] } },
{ "type": "Feature", "properties": { "visible_points": 0, "total_points": 23, "visibility_pct": 0.0 }, "geometry": { "type": "Point", "coordinates": [ -1.624743394961757, 53.643665275196319 ] } },
{ "type": "Feature", "properties": { "visible_points": 0, "total_points": 23, "visibility_pct": 0.0 }, "geometry": { "type": "Point", "coordinates": [ -1.624741801259971, 53.643845033239188 ] } },
{ "type": "Feature", "properties": { "visible_points": 0, "total_points": 23, "visibility_pct": 0.0 }, "geometry": { "type": "Point", "coordinates": [ -1.624740207540847, 53.644024791276635 ] } },
{ "type": "Feature", "properties": { "visible_points": 0, "total_points": 23, "visibility_pct": 0.0 }, "geometry": { "type": "Point", "coordinates": [ -1.624738613804384, 53.644204549308633 ] } },
{ "type": "Feature", "properties": { "visible_points": 0, "total_points": 23, "visibility_pct": 0.0 }, "geometry": { "type": "Point", "coordinates": [ -1.624442469689345, 53.643484575473494 ] } },
{ "type": "Feature", "properties": { "visible_points": 0, "total_points": 23, "visibility_pct": 0.0 }, "geometry": { "type": "Point", "coordinates": [ -1.624440874717415, 53.64366433351735 ] } },
{ "type": "Feature", "properties": { "visible_points": 0, "total_points": 23, "visibility_pct": 0.0 }, "geometry": { "type": "Point", "coordinates": [ -1.624439279728133, 53.643844091555792 ] } },
{ "type": "Feature", "properties": { "visible_points": 0, "total_points": 23, "visibility_pct": 0.0 }, "geometry": { "type": "Point", "coordinates": [ -1.624437684721498, 53.644023849588798 ] } },
{ "type": "Feature", "properties": { "visible_points": 0, "total_points": 23, "visibility_pct": 0.0 }, "geometry": { "type": "Point", "coordinates": [ -1.62443608969751, 53.644203607616376 ] } },
{ "type": "Feature", "properties": { "visible_points": 0, "total_points": 23, "visibility_pct": 0.0 }, "geometry": { "type": "Point", "coordinates": [ -1.624139950749802, 53.643483633034499 ] } },
{ "type": "Feature", "properties": { "visible_points": 0, "total_points": 23, "visibility_pct": 0.0 }, "geometry": { "type": "Point", "coordinates": [ -1.62413835449039, 53.643663391073915 ] } },
{ "type": "Feature", "properties": { "visible_points": 0, "total_points": 23, "visibility_pct": 0.0 }, "geometry": { "type": "Point", "coordinates": [ -1.624136758213611, 53.643843149107923 ] } },
{ "type": "Feature", "properties": { "visible_points": 0, "total_points": 23, "visibility_pct": 0.0 }, "geometry": { "type": "Point", "coordinates": [ -1.624135161919465, 53.644022907136488 ] } },
{ "type": "Feature", "properties": { "visible_points": 0, "total_points": 23, "visibility_pct": 0.0 }, "geometry": { "type": "Point", "coordinates": [ -1.624133565607953, 53.644202665159639 ] } },
{ "type": "Feature", "properties": { "visible_points": 0, "total_points": 23, "visibility_pct": 0.0 }, "geometry": { "type": "Point", "coordinates": [ -1.623837431827589, 53.643482689831046 ] } },
{ "type": "Feature", "properties": { "visible_points": 0, "total_points": 23, "visibility_pct": 0.0 }, "geometry": { "type": "Point", "coordinates": [ -1.623835834280694, 53.643662447866021 ] } },
{ "type": "Feature", "properties": { "visible_points": 0, "total_points": 23, "visibility_pct": 0.0 }, "geometry": { "type": "Point", "coordinates": [ -1.623834236716419, 53.643842205895588 ] } },
{ "type": "Feature", "properties": { "visible_points": 0, "total_points": 23, "visibility_pct": 0.0 }, "geometry": { "type": "Point", "coordinates": [ -1.623832639134764, 53.644021963919712 ] } },
{ "type": "Feature", "properties": { "visible_points": 0, "total_points": 23, "visibility_pct": 0.0 }, "geometry": { "type": "Point", "coordinates": [ -1.623831041535727, 53.644201721938423 ] } },
{ "type": "Feature", "properties": { "visible_points": 0, "total_points": 23, "visibility_pct": 0.0 }, "geometry": { "type": "Point", "coordinates": [ -1.623533314088343, 53.643661503893675 ] } },
{ "type": "Feature", "properties": { "visible_points": 0, "total_points": 23, "visibility_pct": 0.0 }, "geometry": { "type": "Point", "coordinates": [ -1.623531715236572, 53.64384126191878 ] } },
{ "type": "Feature", "properties": { "visible_points": 0, "total_points": 23, "visibility_pct": 0.0 }, "geometry": { "type": "Point", "coordinates": [ -1.623530116367406, 53.644021019938478 ] } },
{ "type": "Feature", "properties": { "visible_points": 0, "total_points": 22, "visibility_pct": 0.0 }, "geometry": { "type": "Point", "coordinates": [ -1.623528517480846, 53.644200777952719 ] } }
]
}
