{
"type": "FeatureCollection",
"name": "Leeds_Tittybottle_Park_summer_vga",
"crs": { "type": "name", "properties": { "name": "urn:ogc:def:crs:OGC:1.3:CRS84" } },
"features": [
{ "type": "Feature", "properties": { "visible_points": 0, "total_points": 2, "visibility_pct": 0.0 }, "geometry": { "type": "Point", "coordinates": [ -1.694423833690039, 53.908638354423104 ] } },
{ "type": "Feature", "properties": { "visible_points": 0, "total_points": 2, "visibility_pct": 0.0 }, "geometry": { "type": "Point", "coordinates": [ -1.694118090206456, 53.908817333673099 ] } },
{ "type": "Feature", "properties": { "visible_points": 0, "total_points": 2, "visibility_pct": 0.0 }, "geometry": { "type": "Point", "coordinates": [ -1.693812344121262, 53.908996312138925 ] } }
]
}
