{
"type": "FeatureCollection",
"name": "Leeds_Parkinsons_Wood_OSM_benches_picnic",
"crs": { "type": "name", "properties": { "name": "urn:ogc:def:crs:OGC:1.3:CRS84" } },
"features": [
{ "type": "Feature", "properties": { "Park Feature": "Bench" }, "geometry": { "type": "Point", "coordinates": [ -1.439622, 53.7815327 ] } }
]
}
