{
"type": "FeatureCollection",
"name": "Calderdale_Beechwood_Park_park_street_lights",
"crs": { "type": "name", "properties": { "name": "urn:ogc:def:crs:OGC:1.3:CRS84" } },
"features": [
{ "type": "Feature", "properties": { "Park Feature": "Street Light" }, "geometry": { "type": "Point", "coordinates": [ -1.865021512093842, 53.753172619306326 ] } },
{ "type": "Feature", "properties": { "Park Feature": "Street Light" }, "geometry": { "type": "Point", "coordinates": [ -1.864993707216141, 53.752856211584167 ] } },
{ "type": "Feature", "properties": { "Park Feature": "Street Light" }, "geometry": { "type": "Point", "coordinates": [ -1.866824805015383, 53.756028313227795 ] } },
{ "type": "Feature", "properties": { "Park Feature": "Street Light" }, "geometry": { "type": "Point", "coordinates": [ -1.867532394699623, 53.755763951740583 ] } },
{ "type": "Feature", "properties": { "Park Feature": "Street Light" }, "geometry": { "type": "Point", "coordinates": [ -1.868066858044425, 53.755570400724594 ] } },
{ "type": "Feature", "properties": { "Park Feature": "Street Light" }, "geometry": { "type": "Point", "coordinates": [ -1.868715122362409, 53.755358097164645 ] } },
{ "type": "Feature", "properties": { "Park Feature": "Street Light" }, "geometry": { "type": "Point", "coordinates": [ -1.86929638510444, 53.755231102746535 ] } },
{ "type": "Feature", "properties": { "Park Feature": "Street Light" }, "geometry": { "type": "Point", "coordinates": [ -1.869920010182729, 53.75513650810452 ] } },
{ "type": "Feature", "properties": { "Park Feature": "Street Light" }, "geometry": { "type": "Point", "coordinates": [ -1.870455671469641, 53.755040916480105 ] } },
{ "type": "Feature", "properties": { "Park Feature": "Street Light" }, "geometry": { "type": "Point", "coordinates": [ -1.871113908534041, 53.754933679970151 ] } }
]
}
