{
"type": "FeatureCollection",
"name": "Kirklees_Birkenshaw_Park_park_street_lights",
"crs": { "type": "name", "properties": { "name": "urn:ogc:def:crs:OGC:1.3:CRS84" } },
"features": [
{ "type": "Feature", "properties": { "Park Feature": "Street Light" }, "geometry": { "type": "Point", "coordinates": [ -1.687188454427781, 53.75774000472137 ] } }
]
}
