{
"type": "FeatureCollection",
"name": "Leeds_Shakespeare_Lawn_Village_Green_Area_summer_vga",
"crs": { "type": "name", "properties": { "name": "urn:ogc:def:crs:OGC:1.3:CRS84" } },
"features": [
{ "type": "Feature", "properties": { "visible_points": 4, "total_points": 5, "visibility_pct": 80.0 }, "geometry": { "type": "Point", "coordinates": [ -1.520104865732029, 53.803681701421503 ] } },
{ "type": "Feature", "properties": { "visible_points": 4, "total_points": 5, "visibility_pct": 80.0 }, "geometry": { "type": "Point", "coordinates": [ -1.520102815745506, 53.803861454356067 ] } },
{ "type": "Feature", "properties": { "visible_points": 4, "total_points": 5, "visibility_pct": 80.0 }, "geometry": { "type": "Point", "coordinates": [ -1.519801190936059, 53.803680485883525 ] } },
{ "type": "Feature", "properties": { "visible_points": 4, "total_points": 5, "visibility_pct": 80.0 }, "geometry": { "type": "Point", "coordinates": [ -1.519799139641168, 53.803860238812646 ] } },
{ "type": "Feature", "properties": { "visible_points": 0, "total_points": 5, "visibility_pct": 0.0 }, "geometry": { "type": "Point", "coordinates": [ -1.519797088323788, 53.804039991736346 ] } },
{ "type": "Feature", "properties": { "visible_points": 4, "total_points": 5, "visibility_pct": 80.0 }, "geometry": { "type": "Point", "coordinates": [ -1.519495463559278, 53.803859022500284 ] } }
]
}
