{
"type": "FeatureCollection",
"name": "Bradford_Coney_Wood_OSM_park_features_general",
"crs": { "type": "name", "properties": { "name": "urn:ogc:def:crs:OGC:1.3:CRS84" } },
"features": [
{ "type": "Feature", "properties": { "Park Feature": "Board" }, "geometry": { "type": "Point", "coordinates": [ -1.668391, 53.7793618 ] } }
]
}
