{
"type": "FeatureCollection",
"name": "Bradford_Peel_Hall_OSM_trees",
"crs": { "type": "name", "properties": { "name": "urn:ogc:def:crs:OGC:1.3:CRS84" } },
"features": [
{ "type": "Feature", "properties": { "Park Feature": "Tree" }, "geometry": { "type": "Point", "coordinates": [ -1.8546083, 53.7723033 ] } },
{ "type": "Feature", "properties": { "Park Feature": "Tree" }, "geometry": { "type": "Point", "coordinates": [ -1.8545432, 53.7722607 ] } }
]
}
