{
"type": "FeatureCollection",
"name": "Calderdale_Sowood_Park_summer_vga",
"crs": { "type": "name", "properties": { "name": "urn:ogc:def:crs:OGC:1.3:CRS84" } },
"features": [
{ "type": "Feature", "properties": { "visible_points": 9, "total_points": 9, "visibility_pct": 100.0 }, "geometry": { "type": "Point", "coordinates": [ -1.884944819352816, 53.663517009304293 ] } },
{ "type": "Feature", "properties": { "visible_points": 9, "total_points": 9, "visibility_pct": 100.0 }, "geometry": { "type": "Point", "coordinates": [ -1.884944336102498, 53.663696774286997 ] } },
{ "type": "Feature", "properties": { "visible_points": 9, "total_points": 9, "visibility_pct": 100.0 }, "geometry": { "type": "Point", "coordinates": [ -1.884943852846849, 53.663876539264294 ] } },
{ "type": "Feature", "properties": { "visible_points": 9, "total_points": 9, "visibility_pct": 100.0 }, "geometry": { "type": "Point", "coordinates": [ -1.884642638484292, 53.663336954369456 ] } },
{ "type": "Feature", "properties": { "visible_points": 9, "total_points": 9, "visibility_pct": 100.0 }, "geometry": { "type": "Point", "coordinates": [ -1.884642153967615, 53.6635167193648 ] } },
{ "type": "Feature", "properties": { "visible_points": 9, "total_points": 9, "visibility_pct": 100.0 }, "geometry": { "type": "Point", "coordinates": [ -1.88464166944563, 53.663696484354766 ] } },
{ "type": "Feature", "properties": { "visible_points": 9, "total_points": 9, "visibility_pct": 100.0 }, "geometry": { "type": "Point", "coordinates": [ -1.884641184918339, 53.663876249339353 ] } },
{ "type": "Feature", "properties": { "visible_points": 9, "total_points": 9, "visibility_pct": 100.0 }, "geometry": { "type": "Point", "coordinates": [ -1.884339974037774, 53.66333666349788 ] } },
{ "type": "Feature", "properties": { "visible_points": 9, "total_points": 9, "visibility_pct": 100.0 }, "geometry": { "type": "Point", "coordinates": [ -1.884339488255425, 53.663516428502518 ] } },
{ "type": "Feature", "properties": { "visible_points": 9, "total_points": 9, "visibility_pct": 100.0 }, "geometry": { "type": "Point", "coordinates": [ -1.884339002467757, 53.663696193501785 ] } }
]
}
