{
"type": "FeatureCollection",
"name": "Leeds_Billing_Hill_OSM_park_features_general",
"crs": { "type": "name", "properties": { "name": "urn:ogc:def:crs:OGC:1.3:CRS84" } },
"features": [
{ "type": "Feature", "properties": { "Park Feature": "Waste Basket" }, "geometry": { "type": "Point", "coordinates": [ -1.6831657, 53.8554119 ] } },
{ "type": "Feature", "properties": { "Park Feature": "Waste Basket" }, "geometry": { "type": "Point", "coordinates": [ -1.6839056, 53.8548904 ] } },
{ "type": "Feature", "properties": { "Park Feature": "Waste Basket" }, "geometry": { "type": "Point", "coordinates": [ -1.684301, 53.855662 ] } },
{ "type": "Feature", "properties": { "Park Feature": "Memorial" }, "geometry": { "type": "Point", "coordinates": [ -1.6838878, 53.8550296 ] } }
]
}
